babkeywords_from_dir.py
babtools_gnutella.py
setup.py
babtools_gnutella.egg-info/PKG-INFO
babtools_gnutella.egg-info/SOURCES.txt
babtools_gnutella.egg-info/dependency_links.txt
babtools_gnutella.egg-info/top_level.txt